<?xml version="1.0" encoding="UTF-8"?>
<!-- logback日志级别 TRACE < DEBUG < INFO < WARN < ERROR -->
<!-- scan：定期扫描配置文件是否变化，变化了自动加载；scanPeriod：扫描间隔时间；debug：为false不输出logback框架本身的日志 -->
<configuration scan="true" scanPeriod="60 seconds" debug="false">
    <springProperty scope="context" name="logPath" source="esbconsole.log.path" defaultValue="${esbconsole.home}/log"/>
    <!-- 定义参数常量 -->
    <!-- 日志级别，小于这个级别的日志不被记录 -->
    <property name="log.level" value="error"/>
    <!-- 日志文件保留多长时间，单位：天 -->
    <property name="log.maxHistory" value="30"/>
    <!-- 日志文件存放的根路径，${catalina.base}是Tomcat实例的根目录 -->
    <property name="log.filePath" value="${logPath}"/>
    <!-- 日志内容的显示格式 -->
    <property name="log.pattern" value="%d{yyyy-MM-dd HH:mm:ss.SSS} [%thread] %-5level %logger{50} - %msg%n"/>
    <!-- springboot默认配置 -->
    <conversionRule conversionWord="clr" converterClass="org.springframework.boot.logging.logback.ColorConverter"/>
    <conversionRule conversionWord="wex"
                    converterClass="org.springframework.boot.logging.logback.WhitespaceThrowableProxyConverter"/>
    <conversionRule conversionWord="wEx"
                    converterClass="org.springframework.boot.logging.logback.ExtendedWhitespaceThrowableProxyConverter"/>
    <property name="CONSOLE_LOG_PATTERN"
              value="${CONSOLE_LOG_PATTERN:-%clr(%d{${LOG_DATEFORMAT_PATTERN:-yyyy-MM-dd HH:mm:ss.SSS}}){faint} %clr(${LOG_LEVEL_PATTERN:-%5p}) %clr(${PID:- }){magenta} %clr(---){faint} %clr([%15.15t]){faint} %clr(%-40.40logger{39}){cyan} %clr(:){faint} %m%n${LOG_EXCEPTION_CONVERSION_WORD:-%wEx}}"/>
    <property name="CONSOLE_LOG_CHARSET" value="${CONSOLE_LOG_CHARSET:-${file.encoding:-UTF-8}}"/>

    <property name="FILE_LOG_PATTERN"
              value="${FILE_LOG_PATTERN:-%d{${LOG_DATEFORMAT_PATTERN:-yyyy-MM-dd HH:mm:ss.SSS}} ${LOG_LEVEL_PATTERN:-%5p} ${PID:- } --- [%t] %-40.40logger{39} : %m%n${LOG_EXCEPTION_CONVERSION_WORD:-%wEx}}"/>
    <property name="FILE_LOG_CHARSET" value="${FILE_LOG_CHARSET:-${file.encoding:-UTF-8}}"/>

    <!-- 控制台输出设置 -->
    <appender name="consoleAppender" class="ch.qos.logback.core.ConsoleAppender">
        <encoder>
            <pattern>${CONSOLE_LOG_PATTERN}</pattern>
        </encoder>
    </appender>

    <!-- fileLogAppender -->
    <appender name="fileLogAppender" class="ch.qos.logback.core.rolling.RollingFileAppender">
        <!-- 文件路径 -->
        <file>${log.filePath}/esbconsole.log</file>
        <!-- 日志记录按天保存，就是每天都会有一个日志文件保存当天的所有日志 -->
        <rollingPolicy class="ch.qos.logback.core.rolling.TimeBasedRollingPolicy">
            <!-- 文件名称 -->
            <fileNamePattern>${log.filePath}/%d{yyyy-MM-dd}/console_%d{yyyy-MM-dd}.log</fileNamePattern>
            <!-- 文件保存时间 -->
            <maxHistory>${log.maxHistory}</maxHistory>
        </rollingPolicy>
        <encoder>
            <pattern>${FILE_LOG_PATTERN}</pattern>
            <charset>${FILE_LOG_CHARSET}</charset>
        </encoder>
    </appender>

    <!-- DEBUG -->
    <appender name="debugAppender" class="ch.qos.logback.core.rolling.RollingFileAppender">
        <!-- 文件路径 -->
        <file>${log.filePath}/debug.log</file>
        <!-- 日志记录按天保存，就是每天都会有一个日志文件保存当天的所有日志 -->
        <rollingPolicy class="ch.qos.logback.core.rolling.TimeBasedRollingPolicy">
            <!-- 文件名称 -->
            <fileNamePattern>${log.filePath}/debug/debug.%d{yyyy-MM-dd}.log.gz</fileNamePattern>
            <!-- 文件保存多久 -->
            <maxHistory>${log.maxHistory}</maxHistory>
        </rollingPolicy>
        <encoder>
            <pattern>${log.pattern}</pattern>
        </encoder>
        <filter class="ch.qos.logback.classic.filter.LevelFilter">
            <level>DEBUG</level>
            <onMatch>ACCEPT</onMatch>
            <onMismatch>DENY</onMismatch>
        </filter>
    </appender>

    <!-- INFO -->
    <appender name="infoAppender" class="ch.qos.logback.core.rolling.RollingFileAppender">
        <!-- 文件路径 -->
        <file>${log.filePath}/info.log</file>
        <rollingPolicy class="ch.qos.logback.core.rolling.TimeBasedRollingPolicy">
            <!-- 文件名称 -->
            <fileNamePattern>${log.filePath}/info/info.%d{yyyy-MM-dd}.log.gz</fileNamePattern>
            <!-- 文件最大保存历史数量 -->
            <maxHistory>${log.maxHistory}</maxHistory>
        </rollingPolicy>
        <encoder>
            <pattern>${log.pattern}</pattern>
        </encoder>
        <filter class="ch.qos.logback.classic.filter.LevelFilter">
            <level>INFO</level>
            <onMatch>ACCEPT</onMatch>
            <onMismatch>DENY</onMismatch>
        </filter>
    </appender>

    <!-- ERROR -->
    <appender name="errorAppender" class="ch.qos.logback.core.rolling.RollingFileAppender">
        <!-- 文件路径 -->
        <file>${log.filePath}/error.log</file>
        <rollingPolicy class="ch.qos.logback.core.rolling.TimeBasedRollingPolicy">
            <!-- 文件名称 -->
            <fileNamePattern>${log.filePath}/error/error.%d{yyyy-MM-dd}.log.gz</fileNamePattern>
            <!-- 文件最大保存历史数量 -->
            <maxHistory>${log.maxHistory}</maxHistory>
        </rollingPolicy>
        <encoder>
            <pattern>${log.pattern}</pattern>
        </encoder>
        <filter class="ch.qos.logback.classic.filter.LevelFilter">
            <level>ERROR</level>
            <onMatch>ACCEPT</onMatch>
            <onMismatch>DENY</onMismatch>
        </filter>
    </appender>

    <!-- 创建logger对象
        name：关注哪个包下的日志信息；level：仅记录哪个级别及以上的日志
        additivity：为true时会将root里的appender-ref也加入进来，level不基于root -->
    <logger name="org.talend.esbconsole.server" level="${log.level}" additivity="true">
        <!--                <appender-ref ref="allAppender"/>-->
        <!--        <appender-ref ref="debugAppender"/>-->
        <!--        <appender-ref ref="infoAppender"/>-->
        <!--        <appender-ref ref="errorAppender"/>-->
    </logger>

    <!-- root：所有logger的父类 -->
    <root level="info">
        <appender-ref ref="consoleAppender"/>
        <appender-ref ref="fileLogAppender"/>
    </root>
</configuration>
